welock_iot/__init__.py
welock_iot/auth_token_manager.py
welock_iot/client.py
welock_iot/const.py
welock_iot/manager.py
welock_iot/models.py
welock_iot/wemq.py
welock_iot-0.0.2.dist-info/licenses/LICENSE
welock_iot-0.0.2.dist-info/METADATA
welock_iot-0.0.2.dist-info/WHEEL
welock_iot-0.0.2.dist-info/top_level.txt
welock_iot-0.0.2.dist-info/RECORD
